nhs_number/__init__.py
nhs_number/constants.py
nhs_number/details.py
nhs_number/generate.py
nhs_number/standardise.py
nhs_number/validate.py
nhs_number-1.3.6.dist-info/LICENSE
nhs_number-1.3.6.dist-info/METADATA
nhs_number-1.3.6.dist-info/WHEEL
nhs_number-1.3.6.dist-info/RECORD
