Metadata-Version: 2.3
Name: nhs-number
Version: 1.3.6
Summary: Python package to provide utilities for NHS Numbers, including validity checks, normalisation, and generation.
License: MIT
Author: Andy Law
Author-email: andy.law@roslin.ed.ac.uk
Requires-Python: >=3.8,<4.0
Classifier: Development Status :: 5 - Production/Stable
Classifier: Intended Audience :: Developers
Classifier: Intended Audience :: Healthcare Industry
Classifier: Intended Audience :: Science/Research
Classifier: License :: OSI Approved :: MIT License
Classifier: Programming Language :: Python :: 3
Classifier: Programming Language :: Python :: 3.8
Classifier: Programming Language :: Python :: 3.9
Classifier: Programming Language :: Python :: 3.10
Classifier: Programming Language :: Python :: 3.11
Classifier: Programming Language :: Python :: 3.12
Classifier: Programming Language :: Python :: 3.13
Classifier: Topic :: Scientific/Engineering :: Mathematics
Classifier: Topic :: Scientific/Engineering :: Medical Science Apps.
Classifier: Topic :: Software Development :: Libraries :: Python Modules
Project-URL: Documentation, https://uk-fci.github.io/nhs-number/
Project-URL: Homepage, https://uk-fci.github.io/nhs-number/
Project-URL: Issue Tracker, https://github.com/uk-fci/nhs-number/issues
Project-URL: Repository, https://github.com/uk-fci/nhs-number
